lbx/__init__.py
lbx/__main__.py
lbx/__version__.py
lbx/cli.py
lbx/core.py
lbx/exceptions.py
lbx/models.py
lbx/settings.py
lbx/services/__init__.py
lbx/services/binary.py
lbx/services/crypto.py
lbx/services/file.py
lbx/services/key_ring.py
lbx-1.1.0.dist-info/METADATA
lbx-1.1.0.dist-info/WHEEL
lbx-1.1.0.dist-info/entry_points.txt
lbx-1.1.0.dist-info/licenses/LICENSE
lbx-1.1.0.dist-info/RECORD
