Metadata-Version: 2.4
Name: lbx
Version: 1.1.0
Summary: A lightweight secret storage vault with CLI and Python API. Stores secrets in encrypted files with master password secured via OS keychain (keyring).
Project-URL: Documentation, https://jd-35656.github.io/lbx/
Project-URL: Issues, https://github.com/jd-35656/lbx/issues
Project-URL: Source, https://github.com/jd-35656/lbx
Author-email: "Jitesh Sahani (JD)" <jitesh.sahani@outlook.com>
License-Expression: MIT
License-File: LICENSE
Keywords: cli,credentials,keychain,keyring,password-manager,secret-management,secrets,security,storage,vault
Classifier: Development Status :: 4 - Beta
Classifier: Environment :: Console
Classifier: Intended Audience :: Developers
Classifier: Intended Audience :: System Administrators
Classifier: Programming Language :: Python
Classifier: Programming Language :: Python :: 3 :: Only
Classifier: Programming Language :: Python :: 3.10
Classifier: Programming Language :: Python :: 3.11
Classifier: Programming Language :: Python :: 3.12
Classifier: Programming Language :: Python :: 3.13
Classifier: Programming Language :: Python :: Implementation :: CPython
Classifier: Programming Language :: Python :: Implementation :: PyPy
Classifier: Topic :: Security
Classifier: Topic :: Security :: Cryptography
Classifier: Topic :: Utilities
Requires-Python: >=3.10
Requires-Dist: argon2-cffi>=23.1.0
Requires-Dist: click>=8.1
Requires-Dist: cryptography>=42.0.0
Requires-Dist: keyring>=25.0.0
Provides-Extra: docs
Requires-Dist: mike>=2.0; extra == 'docs'
Requires-Dist: mkdocs-autorefs>=1.0; extra == 'docs'
Requires-Dist: mkdocs-gen-files>=0.5; extra == 'docs'
Requires-Dist: mkdocs-macros-plugin>=1.0; extra == 'docs'
Requires-Dist: mkdocs-material>=9.4; extra == 'docs'
Requires-Dist: mkdocs>=1.5; extra == 'docs'
Requires-Dist: mkdocstrings-python>=1.8; extra == 'docs'
Requires-Dist: mkdocstrings>=0.24; extra == 'docs'
Requires-Dist: pymdown-extensions>=10.0; extra == 'docs'
Requires-Dist: ruff>=0.1; extra == 'docs'
Requires-Dist: towncrier>=23.0; extra == 'docs'
Provides-Extra: tests
Requires-Dist: pytest-cov>=4.0; extra == 'tests'
Requires-Dist: pytest>=7.4; extra == 'tests'
Provides-Extra: types
Requires-Dist: mypy>=1.8; extra == 'types'
